<?xml version="1.0" encoding="ISO-8859-1"?>
<root>
	<item id="spacecss"><![CDATA[#portal_block_19 { margin-top:15px !important;}]]></item>
	<item id="layoutdata">
		<item id="diy1"><![CDATA[]]></item>
		<item id="diysummarytop"><![CDATA[]]></item>
		<item id="diysummarybottom"><![CDATA[]]></item>
		<item id="diycontenttop"><![CDATA[]]></item>
		<item id="diycontentbottom"><![CDATA[]]></item>
		<item id="diycontentclickbottom"><![CDATA[]]></item>
		<item id="diycontentrelatetop"><![CDATA[]]></item>
		<item id="diycontentrelate"><![CDATA[]]></item>
		<item id=""><![CDATA[]]></item>
		<item id="diycontentcomment"><![CDATA[]]></item>
		<item id="diyrighttop">
			<item id="frame`frameSoo7Z1">
				<item id="attr">
					<item id="name"><![CDATA[frameSoo7Z1]]></item>
					<item id="moveable"><![CDATA[true]]></item>
					<item id="className"><![CDATA[cl_frame_bm frame move-span cl frame-1]]></item>
					<item id="titles"><![CDATA[]]></item>
				</item>
				<item id="column`frameSoo7Z1_left">
					<item id="attr">
						<item id="name"><![CDATA[frameSoo7Z1_left]]></item>
						<item id="className"><![CDATA[column frame-1-c]]></item>
					</item>
					<item id="block`portal_block_18">
						<item id="attr">
							<item id="name"><![CDATA[portal_block_18]]></item>
							<item id="className"><![CDATA[cl_block_bm block move-span]]></item>
							<item id="titles"><![CDATA[]]></item>
						</item>
					</item>
					<item id="block`portal_block_19">
						<item id="attr">
							<item id="name"><![CDATA[portal_block_19]]></item>
							<item id="className"><![CDATA[cl_block_bm block move-span]]></item>
							<item id="titles"><![CDATA[]]></item>
						</item>
					</item>
				</item>
			</item>
		</item>
		<item id="diy2">
			<item id="frame`frameK934P2">
				<item id="attr">
					<item id="name"><![CDATA[frameK934P2]]></item>
					<item id="moveable"><![CDATA[true]]></item>
					<item id="className"><![CDATA[cl_frame_bm frame move-span cl frame-1]]></item>
					<item id="titles"><![CDATA[]]></item>
				</item>
				<item id="column`frameK934P2_left">
					<item id="attr">
						<item id="name"><![CDATA[frameK934P2_left]]></item>
						<item id="className"><![CDATA[column frame-1-c]]></item>
					</item>
					<item id="block`portal_block_20">
						<item id="attr">
							<item id="name"><![CDATA[portal_block_20]]></item>
							<item id="className"><![CDATA[cl_block_bm block move-span]]></item>
							<item id="titles"><![CDATA[]]></item>
						</item>
					</item>
				</item>
			</item>
		</item>
		<item id="diy3"><![CDATA[]]></item>
	</item>
	<item id="blockdata">
		<item id="block">
			<item id="18">
				<item id="bid"><![CDATA[18]]></item>
				<item id="blockclass"><![CDATA[html_html]]></item>
				<item id="blocktype"><![CDATA[0]]></item>
				<item id="name"><![CDATA[ad1]]></item>
				<item id="title"><![CDATA[]]></item>
				<item id="classname"><![CDATA[cl_block_bm]]></item>
				<item id="summary"><![CDATA[<a href="#" target="_black"><img src="/25utf/template/dean_yishou/images/ad1.jpg" /></a>]]></item>
				<item id="uid"><![CDATA[1]]></item>
				<item id="username"><![CDATA[admin]]></item>
				<item id="styleid"><![CDATA[0]]></item>
				<item id="blockstyle"><![CDATA[]]></item>
				<item id="picwidth"><![CDATA[0]]></item>
				<item id="picheight"><![CDATA[0]]></item>
				<item id="target"><![CDATA[blank]]></item>
				<item id="dateformat"><![CDATA[Y-m-d]]></item>
				<item id="dateuformat"><![CDATA[0]]></item>
				<item id="script"><![CDATA[blank]]></item>
				<item id="param">
					<item id="content"><![CDATA[<a href=\"#\" target=\"_black\"><img src=\"/25utf/template/dean_yishou/images/ad1.jpg\" /></a>]]></item>
					<item id="items"><![CDATA[10]]></item>
				</item>
				<item id="shownum"><![CDATA[10]]></item>
				<item id="cachetime"><![CDATA[0]]></item>
				<item id="cachetimerange"><![CDATA[0,0]]></item>
				<item id="punctualupdate"><![CDATA[0]]></item>
				<item id="hidedisplay"><![CDATA[0]]></item>
				<item id="dateline"><![CDATA[1365938092]]></item>
				<item id="notinherited"><![CDATA[0]]></item>
				<item id="isblank"><![CDATA[0]]></item>
			</item>
			<item id="19">
				<item id="bid"><![CDATA[19]]></item>
				<item id="blockclass"><![CDATA[html_html]]></item>
				<item id="blocktype"><![CDATA[0]]></item>
				<item id="name"><![CDATA[ad2]]></item>
				<item id="title"><![CDATA[]]></item>
				<item id="classname"><![CDATA[cl_block_bm]]></item>
				<item id="summary"><![CDATA[<a href="#" target="_black"><img src="/25utf/template/dean_yishou/images/ad2.jpg" /></a>]]></item>
				<item id="uid"><![CDATA[1]]></item>
				<item id="username"><![CDATA[admin]]></item>
				<item id="styleid"><![CDATA[0]]></item>
				<item id="blockstyle"><![CDATA[]]></item>
				<item id="picwidth"><![CDATA[0]]></item>
				<item id="picheight"><![CDATA[0]]></item>
				<item id="target"><![CDATA[blank]]></item>
				<item id="dateformat"><![CDATA[Y-m-d]]></item>
				<item id="dateuformat"><![CDATA[0]]></item>
				<item id="script"><![CDATA[blank]]></item>
				<item id="param">
					<item id="content"><![CDATA[<a href=\"#\" target=\"_black\"><img src=\"/25utf/template/dean_yishou/images/ad2.jpg\" /></a>]]></item>
					<item id="items"><![CDATA[10]]></item>
				</item>
				<item id="shownum"><![CDATA[10]]></item>
				<item id="cachetime"><![CDATA[0]]></item>
				<item id="cachetimerange"><![CDATA[0,0]]></item>
				<item id="punctualupdate"><![CDATA[0]]></item>
				<item id="hidedisplay"><![CDATA[0]]></item>
				<item id="dateline"><![CDATA[1365938092]]></item>
				<item id="notinherited"><![CDATA[0]]></item>
				<item id="isblank"><![CDATA[0]]></item>
			</item>
			<item id="20">
				<item id="bid"><![CDATA[20]]></item>
				<item id="blockclass"><![CDATA[portal_article]]></item>
				<item id="blocktype"><![CDATA[0]]></item>
				<item id="name"><![CDATA[foodlist]]></item>
				<item id="title"><![CDATA[]]></item>
				<item id="classname"><![CDATA[cl_block_bm]]></item>
				<item id="summary"><![CDATA[]]></item>
				<item id="uid"><![CDATA[1]]></item>
				<item id="username"><![CDATA[admin]]></item>
				<item id="styleid"><![CDATA[119]]></item>
				<item id="blockstyle"><![CDATA[]]></item>
				<item id="picwidth"><![CDATA[95]]></item>
				<item id="picheight"><![CDATA[72]]></item>
				<item id="target"><![CDATA[blank]]></item>
				<item id="dateformat"><![CDATA[Y-m-d]]></item>
				<item id="dateuformat"><![CDATA[0]]></item>
				<item id="script"><![CDATA[articlehot]]></item>
				<item id="param">
					<item id="catid">
						<item id="0"><![CDATA[0]]></item>
					</item>
					<item id="picrequired"><![CDATA[1]]></item>
					<item id="orderby"><![CDATA[viewnum]]></item>
					<item id="titlelength"><![CDATA[15]]></item>
					<item id="summarylength"><![CDATA[40]]></item>
					<item id="items"><![CDATA[6]]></item>
				</item>
				<item id="shownum"><![CDATA[6]]></item>
				<item id="cachetime"><![CDATA[3600]]></item>
				<item id="cachetimerange"><![CDATA[]]></item>
				<item id="punctualupdate"><![CDATA[0]]></item>
				<item id="hidedisplay"><![CDATA[0]]></item>
				<item id="dateline"><![CDATA[1366096218]]></item>
				<item id="notinherited"><![CDATA[0]]></item>
				<item id="isblank"><![CDATA[0]]></item>
			</item>
		</item>
		<item id="style">
			<item id="119">
				<item id="styleid"><![CDATA[119]]></item>
				<item id="blockclass"><![CDATA[portal_article]]></item>
				<item id="name"><![CDATA[dean工作室亿手网-首页foodlist]]></item>
				<item id="template">
					<item id="raw"><![CDATA[[loop]
	<li>
         <div class="imgs"><a href="{url}"{target}><img src="{pic}" width="{picwidth}" height="{picheight}" /></a></div>
         <div class="infos"><a href="{url}"{target}>{title}</a><p>{summary}</p></div>
         <div class="clear"></div>
        </li>
[/loop]
]]></item>
					<item id="footer"><![CDATA[]]></item>
					<item id="header"><![CDATA[]]></item>
					<item id="indexplus">
					</item>
					<item id="index">
					</item>
					<item id="orderplus">
					</item>
					<item id="order">
					</item>
					<item id="loopplus">
					</item>
					<item id="loop"><![CDATA[<li>
         <div class="imgs"><a href="{url}"{target}><img src="{pic}" width="{picwidth}" height="{picheight}" /></a></div>
         <div class="infos"><a href="{url}"{target}>{title}</a><p>{summary}</p></div>
         <div class="clear"></div>
        </li>]]></item>
				</item>
				<item id="hash"><![CDATA[b0883702]]></item>
				<item id="getpic"><![CDATA[1]]></item>
				<item id="getsummary"><![CDATA[1]]></item>
				<item id="makethumb"><![CDATA[1]]></item>
				<item id="settarget"><![CDATA[1]]></item>
				<item id="fields">
					<item id="0"><![CDATA[url]]></item>
					<item id="1"><![CDATA[pic]]></item>
					<item id="2"><![CDATA[title]]></item>
					<item id="3"><![CDATA[summary]]></item>
				</item>
				<item id="moreurl"><![CDATA[0]]></item>
			</item>
		</item>
	</item>
</root>